koboldapi/__init__.py
koboldapi/chunking/__init__.py
koboldapi/chunking/chunker_regex.py
koboldapi/chunking/processor.py
koboldapi/core/__init__.py
koboldapi/core/api.py
koboldapi/core/core.py
koboldapi/core/default_templates.py
koboldapi/core/templates.py
koboldapi/image/__init__.py
koboldapi/image/processor.py
koboldapi-0.5.4.dist-info/LICENSE
koboldapi-0.5.4.dist-info/METADATA
koboldapi-0.5.4.dist-info/WHEEL
koboldapi-0.5.4.dist-info/entry_points.txt
koboldapi-0.5.4.dist-info/top_level.txt
koboldapi-0.5.4.dist-info/RECORD
