Metadata-Version: 2.2
Name: koboldapi
Version: 0.5.4
Summary: Python library for interacting with KoboldCPP API
Author: jabberjabberjabber
License: GNU General Public License v3.0
Requires-Python: >=3.8
License-File: LICENSE
Requires-Dist: requests
Requires-Dist: aiohttp
Requires-Dist: pillow
Requires-Dist: pillow-heif
Requires-Dist: rawpy
Requires-Dist: extractous
Requires-Dist: jinja2
Requires-Dist: regex
Provides-Extra: dev
Requires-Dist: black; extra == "dev"
Requires-Dist: isort; extra == "dev"
Requires-Dist: flake8; extra == "dev"
Dynamic: requires-python
